bits/__init__.py
bits/slack/__init__.py
bits/slack/bitsdb.py
bits/slack/client.py
bits/slack/scim.py
bits/slack/update.py
bits_slack-1.0.22.dist-info/METADATA
bits_slack-1.0.22.dist-info/WHEEL
bits_slack-1.0.22.dist-info/top_level.txt
bits_slack-1.0.22.dist-info/RECORD
