Metadata-Version: 2.1
Name: bits-slack
Version: 1.0.22
Summary: BITS Slack
Home-page: UNKNOWN
Author: Lukas Karlsson
Author-email: karlsson@broadinstitute.org
License: Apache Software License
Platform: UNKNOWN
Requires-Dist: slackclient
Requires-Dist: slack-scim
